Adame/AdameCore.py
Adame/__init__.py
adame-2.0.1.dist-info/METADATA
adame-2.0.1.dist-info/WHEEL
adame-2.0.1.dist-info/entry_points.txt
adame-2.0.1.dist-info/top_level.txt
adame-2.0.1.dist-info/RECORD
