Metadata-Version: 2.4
Name: Adame
Version: 2.0.1
Summary: Adame is a tool to manage docker-applications as part in a Linux-environment.
Home-page: https://github.com/anionDev/Adame
Author: Marius Göcke
Author-email: marius.goecke@gmail.com
Keywords: release build management
Classifier: Intended Audience :: Developers
Classifier: Topic :: Software Development :: Libraries :: Python Modules
Classifier: Programming Language :: Python :: 3.10
Classifier: License :: OSI Approved :: MIT License
Classifier: Operating System :: POSIX :: Linux
Classifier: Operating System :: Microsoft :: Windows :: Windows 10
Classifier: Topic :: System :: Logging
Classifier: Topic :: System :: Monitoring
Classifier: Topic :: System :: Systems Administration
Classifier: Topic :: Terminals
Classifier: Topic :: Utilities
Requires-Python: >=3.10
Requires-Dist: packaging>=25.0.0
Requires-Dist: psutil>=7.2.1
Requires-Dist: PyYAML>=6.0.3
Requires-Dist: ScriptCollection>=4.2.31
